marketswimmer/__init__.py
marketswimmer/__main__.py
marketswimmer/cli.py
marketswimmer/process_financial_data.py
marketswimmer/core/__init__.py
marketswimmer/core/analysis.py
marketswimmer/core/download_manager.py
marketswimmer/core/fair_value.py
marketswimmer/core/owner_earnings.py
marketswimmer/core/workflow.py
marketswimmer/gui/__init__.py
marketswimmer/gui/main_window.py
marketswimmer/visualization/__init__.py
marketswimmer/visualization/charts.py
marketswimmer-2.5.1.dist-info/licenses/LICENSE
marketswimmer-2.5.1.dist-info/METADATA
marketswimmer-2.5.1.dist-info/WHEEL
marketswimmer-2.5.1.dist-info/entry_points.txt
marketswimmer-2.5.1.dist-info/top_level.txt
marketswimmer-2.5.1.dist-info/RECORD
