Metadata-Version: 2.4
Name: marketswimmer
Version: 2.5.1
Summary: Warren Buffett's Owner Earnings Analysis Tool - Calculate true economic earnings for any stock
Home-page: https://github.com/jeremevans/MarketSwimmer
Author: Jeremy Evans
Author-email: Jeremy Evans <jeremyevans@hey.com>
License: MIT
Project-URL: Homepage, https://github.com/jeremevans/MarketSwimmer
Project-URL: Bug Reports, https://github.com/jeremevans/MarketSwimmer/issues
Project-URL: Source, https://github.com/jeremevans/MarketSwimmer
Project-URL: Documentation, https://github.com/jeremevans/MarketSwimmer/blob/main/README.md
Keywords: finance,warren-buffett,owner-earnings,stocks,investment,financial-analysis
Classifier: Development Status :: 4 - Beta
Classifier: Intended Audience :: Financial and Insurance Industry
Classifier: Intended Audience :: Developers
Classifier: Topic :: Office/Business :: Financial :: Investment
Classifier: License :: OSI Approved :: MIT License
Classifier: Programming Language :: Python :: 3
Classifier: Programming Language :: Python :: 3.8
Classifier: Programming Language :: Python :: 3.9
Classifier: Programming Language :: Python :: 3.10
Classifier: Programming Language :: Python :: 3.11
Classifier: Programming Language :: Python :: 3.12
Classifier: Operating System :: OS Independent
Requires-Python: >=3.8
License-File: LICENSE
Requires-Dist: pandas>=1.3.0
Requires-Dist: matplotlib>=3.5.0
Requires-Dist: seaborn>=0.11.0
Requires-Dist: numpy>=1.21.0
Requires-Dist: openpyxl>=3.0.0
Requires-Dist: PyQt6>=6.0.0
Requires-Dist: typer>=0.9.0
Requires-Dist: rich>=13.0.0
Requires-Dist: requests>=2.25.0
Requires-Dist: click>=8.0.0
Requires-Dist: shellingham>=1.3.0
Provides-Extra: dev
Requires-Dist: pytest>=7.0.0; extra == "dev"
Requires-Dist: black>=22.0.0; extra == "dev"
Requires-Dist: flake8>=4.0.0; extra == "dev"
Requires-Dist: mypy>=0.950; extra == "dev"
Provides-Extra: gui
Requires-Dist: PyQt6>=6.0.0; extra == "gui"
Dynamic: author
Dynamic: home-page
Dynamic: license-file
Dynamic: requires-python
